envprofile/__init__.py
envprofile/__main__.py
envprofile/cli.py
envprofile/core.py
envprofile/main.py
envprofile-0.1.0.dist-info/licenses/LICENSE
envprofile-0.1.0.dist-info/METADATA
envprofile-0.1.0.dist-info/WHEEL
envprofile-0.1.0.dist-info/entry_points.txt
envprofile-0.1.0.dist-info/top_level.txt
envprofile-0.1.0.dist-info/RECORD
